djangocms_text_ckeditor5/__init__.py
djangocms_text_ckeditor5/static/djangocms_text_ckeditor5/bundles/bundle.ckeditor5.min.js
djangocms_text_ckeditor5/static/djangocms_text_ckeditor5/bundles/bundle.ckeditor5.min.js.map
djangocms_text_ckeditor5/static/djangocms_text_ckeditor5/css/cms.ckeditor5.css
djangocms_text_ckeditor5/static/djangocms_text_ckeditor5/css/cms.linkfield.css
djangocms_text_ckeditor5-0.2.6.dist-info/METADATA
djangocms_text_ckeditor5-0.2.6.dist-info/WHEEL
djangocms_text_ckeditor5-0.2.6.dist-info/licenses/LICENSE
djangocms_text_ckeditor5-0.2.6.dist-info/RECORD
