Metadata-Version: 2.4
Name: djangocms-text-ckeditor5
Version: 0.2.6
Summary: CKEditor 5 Rich Text Plugin for django CMS
Project-URL: Homepage, https://github.com/django-cms/djangocms-text-ckeditor5
Author-email: Django CMS Association and contributors <info@django-cms.org>
Maintainer-email: Django CMS Association and contributors <info@django-cms.org>
License: LGPL 2
License-File: LICENSE
Classifier: Development Status :: 5 - Production/Stable
Classifier: Environment :: Web Environment
Classifier: Framework :: Django CMS
Classifier: Framework :: Django CMS :: 3.11
Classifier: Framework :: Django CMS :: 4.0
Classifier: Framework :: Django CMS :: 4.1
Classifier: Intended Audience :: Developers
Classifier: License :: OSI Approved :: BSD License
Classifier: Operating System :: OS Independent
Classifier: Programming Language :: Python
Classifier: Topic :: Internet :: WWW/HTTP
Classifier: Topic :: Internet :: WWW/HTTP :: Dynamic Content
Classifier: Topic :: Software Development
Classifier: Topic :: Software Development :: Libraries
Requires-Python: >=3.9
Requires-Dist: djangocms-text>=0.5
